vceepayment/__init__.py
vceepayment/encryption.py
vceepayment/models.py
vceepayment/pages.py
vceepayment/tests.py
vceepayment/_builtin/__init__.py
vceepayment/_builtin/__pycache__/__init__.cpython-38.pyc
vceepayment/static/vceepayment/vcee_logo.jpg
vceepayment/templates/vceepayment/ConfirmationPage.html
vceepayment/templates/vceepayment/PaymentInfos.html
vceepayment/templates/vceepayment/admin_report.html
otree_vcee_payment-0.9.2.dist-info/METADATA
otree_vcee_payment-0.9.2.dist-info/WHEEL
otree_vcee_payment-0.9.2.dist-info/top_level.txt
otree_vcee_payment-0.9.2.dist-info/RECORD
