Metadata-Version: 2.1
Name: otree-vcee-payment
Version: 0.9.2
Summary: VCEE Payment App for oTree
Home-page: https://vcee.univie.ac.at/
Author: 'Philipp Külpmann, Geoffrey Castillo'
Author-email: vcee@univie.ac.at
Classifier: Development Status :: 3 - Alpha
Classifier: Programming Language :: Python :: 3
Classifier: Programming Language :: Python :: 3.6
Classifier: Programming Language :: Python :: 3.7
Classifier: Programming Language :: Python :: 3.8
Classifier: Environment :: Web Environment
Classifier: Framework :: Django
Classifier: Operating System :: OS Independent
Requires-Dist: schwifty (>=2021.1.0)
Requires-Dist: otree (<5)
Requires-Dist: cryptography (>=3.4.6)
